<?xml version="1.0" encoding="utf-8"?>
<data>
  <carPark>
    <systemCodeNumber>CP-01</systemCodeNumber>
    <occupancy>0</occupancy>
    <occupancyPercentage>0</occupancyPercentage>
    <date>2014-03-31</date>
  </carPark>
  <carPark>
    <systemCodeNumber>CP-02</systemCodeNumber>
    <occupancy>4</occupancy>
    <occupancyPercentage>.44</occupancyPercentage>
    <date>2014-03-31</date>
  </carPark>
  <carPark>
    <systemCodeNumber>CP-03</systemCodeNumber>
    <occupancy>329</occupancy>
    <occupancyPercentage>83</occupancyPercentage>
    <date>2014-07-29</date>
  </carPark>
  <carPark>
    <systemCodeNumber>CP-04</systemCodeNumber>
    <occupancy>166</occupancy>
    <occupancyPercentage>45.48</occupancyPercentage>
    <date>2014-02-28</date>
  </carPark>
  <carPark>
    <systemCodeNumber>CP-05</systemCodeNumber>
    <occupancy>76</occupancy>
    <occupancyPercentage>55</occupancyPercentage>
    <date>2014-07-29</date>
  </carPark>
  <carPark>
    <systemCodeNumber>CP-06</systemCodeNumber>
    <occupancy>49</occupancy>
    <occupancyPercentage>30</occupancyPercentage>
    <date>2014-07-29</date>
  </carPark>
  <carPark>
    <systemCodeNumber>CP-07</systemCodeNumber>
    <occupancy>145</occupancy>
    <occupancyPercentage>45</occupancyPercentage>
    <date>2014-07-29</date>
  </carPark>
  <carPark>
    <systemCodeNumber>CP-08</systemCodeNumber>
    <occupancy>-123</occupancy>
    <occupancyPercentage>-246</occupancyPercentage>
    <date>2014-07-23</date>
  </carPark>
  <carPark>
    <systemCodeNumber>CP-09</systemCodeNumber>
    <occupancy>228</occupancy>
    <occupancyPercentage>46</occupancyPercentage>
    <date>2014-07-29</date>
  </carPark>
  <carPark>
    <systemCodeNumber>CP-10</systemCodeNumber>
    <occupancy>912</occupancy>
    <occupancyPercentage>64.23</occupancyPercentage>
    <date>2014-07-29</date>
  </carPark>
</data>
